stein_thinning/__init__.py
stein_thinning/kernel.py
stein_thinning/stein.py
stein_thinning/thinning.py
stein_thinning/demo/gmm.py
stein_thinning/demo/gradient_free.py
stein_thinning/demo/pystan.py
stein_thinning/demo/data/scr.csv
stein_thinning/demo/data/smp.csv
stein_thinning-0.2.0.dist-info/LICENSE
stein_thinning-0.2.0.dist-info/METADATA
stein_thinning-0.2.0.dist-info/WHEEL
stein_thinning-0.2.0.dist-info/top_level.txt
stein_thinning-0.2.0.dist-info/RECORD
