Metadata-Version: 2.1
Name: stein_thinning
Version: 0.2.0
Summary: Optimally compress sampling algorithm outputs
Author: Stein Thinning team
License: Copyright 2024 Stein Thinning team
Project-URL: Homepage, https://github.com/wilson-ye-chen/stein_thinning
Keywords: mcmc,Stein,thinning
Classifier: License :: OSI Approved :: MIT License
Classifier: Programming Language :: Python
Classifier: Programming Language :: Python :: 3
Requires-Python: >=3.7
License-File: LICENSE
Requires-Dist: numpy
Requires-Dist: scipy
Provides-Extra: demo
Requires-Dist: matplotlib; extra == "demo"
Requires-Dist: pystan; extra == "demo"
Provides-Extra: dev
Requires-Dist: pytest; extra == "dev"
Requires-Dist: bumpver; extra == "dev"
Requires-Dist: sphinx; extra == "dev"
